{
    "select": [
        {
            "input_device": "keyboard",
            "key": "return",
            "type": "action"
        },
        {
            "input_device": "controller",
            "type": "action_button",
            "value": "a"
        }
    ],
    "pause": [
        {
            "input_device": "keyboard",
            "key": "escape",
            "type": "action"
        },
        {
            "input_device": "keyboard",
            "key": "p",
            "type": "action"
        },
        {
            "input_device": "controller",
            "type": "action_button",
            "value": "menu"
        }
    ],
    "ship_forward": [
        {
            "input_device": "keyboard",
            "key": "w",
            "type": "hold"
        },
        {
            "input_device": "controller",
            "type": "hold_button",
            "value": "r_bumper"
        },
        {
            "input_device": "controller",
            "type": "trigger",
            "side": "left",
            "value": 0.5
        }
    ],
    "ship_backward": [
        {
            "input_device": "keyboard",
            "key": "s",
            "type": "hold"
        },
        {
            "input_device": "controller",
            "type": "hold_button",
            "value": "l_bumper"
        }
    ],
    "shoot": [
        {
            "input_device": "keyboard",
            "key": "space",
            "type": "action"
        },
        {
            "input_device": "controller",
            "type": "action_button",
            "value": "a"
        }
    ],
    "left": [
        {
            "input_device": "keyboard",
            "key": "a",
            "type": "hold"
        },
        {
            "input_device": "controller",
            "type": "stick",
            "side": "left",
            "axis": "x",
            "value": -0.5
        },
        {
            "input_device": "controller",
            "type": "hold_button",
            "value": "d_left"
        }
    ],
    "right": [
        {
            "input_device": "keyboard",
            "key": "d",
            "type": "hold"
        },
        {
            "input_device": "controller",
            "type": "stick",
            "side": "left",
            "axis": "x",
            "value": 0.5
        },
        {
            "input_device": "controller",
            "type": "hold_button",
            "value": "d_right"
        }
    ]
}